toyllm/__init__.py
toyllm/dataset.py
toyllm/device.py
toyllm/model/__init__.py
toyllm/model/config.py
toyllm/model/generate.py
toyllm/model/gpt.py
toyllm/model/loss.pdf
toyllm/model/train.py
toyllm/tokenizer.py
toyllm-0.1.0.dist-info/LICENSE
toyllm-0.1.0.dist-info/METADATA
toyllm-0.1.0.dist-info/WHEEL
toyllm-0.1.0.dist-info/RECORD
